pylatt/__about__.py
pylatt/__init__.py
pylatt/core.py
pylatt/isocontour.py
pylatt/kl.py
pylatt/optimize.py
pylatt-1.0.0.dist-info/LICENSE.txt
pylatt-1.0.0.dist-info/METADATA
pylatt-1.0.0.dist-info/WHEEL
pylatt-1.0.0.dist-info/top_level.txt
pylatt-1.0.0.dist-info/RECORD
