Metadata-Version: 2.1
Name: pylatt
Version: 1.0.0
Summary: Mechanical lattices
Home-page: https://gitlab.com/benvial/pylatt
Author: Benjamin Vial
License: GPL-3.0-or-later
Project-URL: Code, https://gitlab.com/benvial/pylatt
Project-URL: Documentation, https://benvial.gitlab.io/pylatt
Project-URL: Issues, https://gitlab.com/benvial/pylatt/issues
Keywords: lattices,auto-differentiation,linear algebra
Classifier: Development Status :: 4 - Beta
Classifier: Intended Audience :: Science/Research
Classifier: License :: OSI Approved :: GNU General Public License v3 or later (GPLv3+)
Classifier: Operating System :: OS Independent
Classifier: Programming Language :: Python
Classifier: Programming Language :: Python :: 3
Classifier: Programming Language :: Python :: 3.6
Classifier: Programming Language :: Python :: 3.7
Classifier: Programming Language :: Python :: 3.8
Classifier: Programming Language :: Python :: 3.9
Classifier: Programming Language :: Python :: 3.10
Classifier: Topic :: Scientific/Engineering
Classifier: Topic :: Scientific/Engineering :: Mathematics
Classifier: Topic :: Utilities
Requires-Python: >=3.6
License-File: LICENSE.txt
Requires-Dist: matplotlib
Requires-Dist: numpy
Requires-Dist: scipy
Requires-Dist: tqdm
Requires-Dist: importlib-metadata ; python_version < "3.8"
Provides-Extra: diff
Requires-Dist: numdiff (>=0.0.1) ; extra == 'diff'
Provides-Extra: full
Requires-Dist: pylatt[diff] ; extra == 'full'
Requires-Dist: pylatt[opt] ; extra == 'full'
Requires-Dist: pylatt[isocontour] ; extra == 'full'
Provides-Extra: isocontour
Requires-Dist: scikit-image ; extra == 'isocontour'
Provides-Extra: opt
Requires-Dist: nlopt ; extra == 'opt'
